<?xml version="1.0"?>
<?xml-stylesheet type="text/xsl" href="billres.xsl"?>
<!DOCTYPE bill PUBLIC "-//US Congress//DTDs/bill.dtd//EN" "bill.dtd">
<bill bill-stage="Introduced-in-House" dms-id="H6E444730AF244797BE163ED46C58ACCD" public-private="public" key="H" bill-type="olc"><metadata xmlns:dc="http://purl.org/dc/elements/1.1/">
<dublinCore>
<dc:title>118 HR 5691 IH: Drought Assistance Improvement Act</dc:title>
<dc:publisher>U.S. House of Representatives</dc:publisher>
<dc:date>2023-09-26</dc:date>
<dc:format>text/xml</dc:format>
<dc:language>EN</dc:language>
<dc:rights>Pursuant to Title 17 Section 105 of the United States Code, this file is not subject to copyright protection and is in the public domain.</dc:rights>
</dublinCore>
</metadata>
<form>
<distribution-code display="yes">I</distribution-code><congress display="yes">118th CONGRESS</congress><session display="yes">1st Session</session><legis-num display="yes">H. R. 5691</legis-num><current-chamber>IN THE HOUSE OF REPRESENTATIVES</current-chamber><action display="yes"><action-date date="20230926">September 26, 2023</action-date><action-desc><sponsor name-id="L000595">Ms. Letlow</sponsor> introduced the following bill; which was referred to the <committee-name committee-id="HAG00">Committee on Agriculture</committee-name></action-desc></action><legis-type>A BILL</legis-type><official-title display="yes">To improve drought related disaster assistance programs of the Department of Agriculture, and for other purposes.</official-title></form><legis-body id="H6A54C985AC284E159C0E21F9D528F47D" style="OLC"><section id="HA466B2D4524A483493B9960556205AC2" section-type="section-one"><enum>1.</enum><header>Short title</header><text display-inline="no-display-inline"> This Act may be cited as the <quote><short-title>Drought Assistance Improvement Act</short-title></quote></text></section><section id="HEE20973B336947F69EDB710B2D7EA23C"><enum>2.</enum><header>Livestock forage disaster program</header><text display-inline="no-display-inline">Section 1501(c)(3)(D)(ii)(I) of the Agricultural Act of 2014 (<external-xref legal-doc="usc" parsable-cite="usc/7/9081">7 U.S.C. 9081(c)(3)(D)(ii)(I)</external-xref>) is amended—</text><paragraph id="HFFC2B6C4F2334D3392A95DAABDFD006B"><enum>(1)</enum><text>by striking <quote>at least 8 consecutive</quote> and inserting the following: </text><quoted-block id="HFC775C5D8ACD4290BFE2E290D2B09005" style="OLC" display-inline="yes-display-inline"><text>not less than—</text><item id="H8D4721C84A634108A60ABF8A4EA6EDBA"><enum>(aa)</enum><text>4 consecutive weeks during the normal grazing period for the county, as determined by the Secretary, shall be eligible to receive assistance under this paragraph in an amount equal to 1 monthly payment using the monthly payment rate determined under subparagraph (B); or</text></item><item id="HAC008334C12741BF971B70BF5C318A20"><enum>(bb)</enum><text>8 consecutive</text></item><after-quoted-block>; and</after-quoted-block></quoted-block></paragraph><paragraph id="H49F2BBF473C94A07878854FBB5B75693"><enum>(2)</enum><text>in item (bb) (as so designated), by striking <quote>1 monthly payment</quote> and inserting <quote>2 monthly payments</quote>.</text></paragraph></section><section id="H59956207835D49D5B92FD0D3FCB5E0D8"><enum>3.</enum><header>Emergency assistance for livestock, honey bees, and farm-raised fish program</header><subsection id="H0F6F67767F164C73BC71187CC28A463A"><enum>(a)</enum><header>Documentation standards</header><text display-inline="yes-display-inline">Section 1501(d) of the Agricultural Act of 2014 (<external-xref legal-doc="usc" parsable-cite="usc/7/9081">7 U.S.C. 9081(d)</external-xref>) is amended—</text><paragraph id="H529CA792F76E40E594CE4C32DE167E76"><enum>(1)</enum><text>in paragraph (1), by inserting <quote>drought,</quote> after <quote>adverse weather,</quote>;</text></paragraph><paragraph id="H7BA3DA4A068A41D08DC315AE78BFE934"><enum>(2)</enum><text>in paragraph (2), by inserting <quote>adverse weather or drought,</quote> after <quote>disease,</quote>; and</text></paragraph><paragraph id="H83850A9CB2984904967CEA55E13FB7EA"><enum>(3)</enum><text>by adding at the end the following:</text><quoted-block id="HDBFE8769332049A38313CBCD5E7A1CC5" style="OLC"><paragraph id="HD90B5D135B7A4764AD01E5F7620419DA"><enum>(5)</enum><header>Documentation standards</header><text display-inline="yes-display-inline">For purposes of this subsection, the Secretary, in consultation with eligible producers of farm-raised fish, shall establish a documentation standard for each of the following:</text><subparagraph id="HD295092F857642479519B4045B5369D1"><enum>(A)</enum><text>Collecting data.</text></subparagraph><subparagraph id="H26D0F78CD73F4D1EB745F990E9610F12"><enum>(B)</enum><text>Production of crawfish, as related to reductions in harvest. </text></subparagraph><subparagraph id="H5BBAD94E2B114C15A971C6C9BFDA7BBC"><enum>(C)</enum><text>Defining loss conditions due to drought. </text></subparagraph></paragraph><after-quoted-block>.</after-quoted-block></quoted-block></paragraph></subsection><subsection id="H92977E023EE848B18C7DFF210EF33834"><enum>(b)</enum><header>Reduced crawfish harvest eligibility</header><text display-inline="yes-display-inline">Subsection 1501(d)(2) of the Agricultural Act of 2014 (<external-xref legal-doc="usc" parsable-cite="usc/7/9081">7 U.S.C. 9081(d)(2)</external-xref>) is further amended by inserting <quote>and loss of crawfish harvest due to adverse weather or drought</quote> after <quote>cattle tick fever</quote>.</text></subsection></section></legis-body></bill> 

