<?xml version="1.0" encoding="utf-8" standalone="no"?>
<billStatus>
  <version>3.0.0</version>
  <bill>
    <number>7566</number>
    <updateDate>2025-03-03T20:01:49Z</updateDate>
    <updateDateIncludingText>2025-03-03T20:01:49Z</updateDateIncludingText>
    <originChamber>House</originChamber>
    <originChamberCode>H</originChamberCode>
    <type>HR</type>
    <introducedDate>2024-03-06</introducedDate>
    <congress>118</congress>
    <cdata>
      <constitutionalAuthorityStatementText>&lt;pre&gt;[Congressional Record Volume 170, Number 40 (Wednesday, March 6, 2024)][House]From the Congressional Record Online through the Government Publishing Office [&lt;a href="https://www.gpo.gov"&gt;www.gpo.gov&lt;/a&gt;]By Mr. LUTTRELL:H.R. 7566.Congress has the power to enact this legislation pursuantto the following:Article 1, Section 8. To make laws which shall be necessaryand proper for carrying into execution the foregoing powers,and all other powers vested by this Constitution in thegovernment of the United States, or in any department orofficer thereof.The single subject of this legislation is:Homeland Secuity.[Page H999]&lt;/pre&gt;</constitutionalAuthorityStatementText>
    </cdata>
    <committees>
      <item>
        <systemCode>hshm00</systemCode>
        <name>Homeland Security Committee</name>
        <chamber>House</chamber>
        <type>Standing</type>
        <subcommittees>
          <item>
            <systemCode>hshm11</systemCode>
            <name>Border Security and Enforcement Subcommittee</name>
            <activities>
              <item>
                <name>Referred to</name>
                <date>2024-03-06T21:40:20Z</date>
              </item>
            </activities>
          </item>
          <item>
            <systemCode>hshm05</systemCode>
            <name>Counterterrorism and Intelligence Subcommittee</name>
            <activities>
              <item>
                <name>Referred to</name>
                <date>2024-03-06T21:40:20Z</date>
              </item>
            </activities>
          </item>
        </subcommittees>
        <activities>
          <item>
            <name>Referred To</name>
            <date>2024-03-06T15:00:45Z</date>
          </item>
        </activities>
      </item>
    </committees>
    <actions>
      <item>
        <actionDate>2024-03-06</actionDate>
        <committees>
          <item>
            <systemCode>hshm11</systemCode>
            <name>Border Security and Enforcement Subcommittee</name>
          </item>
        </committees>
        <sourceSystem>
          <code>1</code>
          <name>House committee actions</name>
        </sourceSystem>
        <text>Referred to the Subcommittee on Border Security and Enforcement.</text>
        <type>Committee</type>
      </item>
      <item>
        <actionDate>2024-03-06</actionDate>
        <committees>
          <item>
            <systemCode>hshm05</systemCode>
            <name>Counterterrorism and Intelligence Subcommittee</name>
          </item>
        </committees>
        <sourceSystem>
          <code>1</code>
          <name>House committee actions</name>
        </sourceSystem>
        <text>Referred to the Subcommittee on Counterterrorism, Law Enforcement, and Intelligence.</text>
        <type>Committee</type>
      </item>
      <item>
        <actionDate>2024-03-06</actionDate>
        <text>Referred to the House Committee on Homeland Security.</text>
        <type>IntroReferral</type>
        <actionCode>H11100</actionCode>
        <sourceSystem>
          <code>2</code>
          <name>House floor actions</name>
        </sourceSystem>
        <committees>
          <item>
            <systemCode>hshm00</systemCode>
            <name>Homeland Security Committee</name>
          </item>
        </committees>
      </item>
      <item>
        <actionDate>2024-03-06</actionDate>
        <text>Introduced in House</text>
        <type>IntroReferral</type>
        <actionCode>Intro-H</actionCode>
        <sourceSystem>
          <code>9</code>
          <name>Library of Congress</name>
        </sourceSystem>
      </item>
      <item>
        <actionDate>2024-03-06</actionDate>
        <text>Introduced in House</text>
        <type>IntroReferral</type>
        <actionCode>1000</actionCode>
        <sourceSystem>
          <code>9</code>
          <name>Library of Congress</name>
        </sourceSystem>
      </item>
    </actions>
    <sponsors>
      <item>
        <bioguideId>L000603</bioguideId>
        <fullName>Rep. Luttrell, Morgan [R-TX-8]</fullName>
        <firstName>Morgan</firstName>
        <lastName>Luttrell</lastName>
        <party>R</party>
        <state>TX</state>
        <district>8</district>
        <isByRequest>N</isByRequest>
      </item>
    </sponsors>
    <cosponsors>
      <item>
        <bioguideId>M001157</bioguideId>
        <fullName>Rep. McCaul, Michael T. [R-TX-10]</fullName>
        <firstName>Michael</firstName>
        <lastName>McCaul</lastName>
        <party>R</party>
        <state>TX</state>
        <middleName>T.</middleName>
        <district>10</district>
        <sponsorshipDate>2024-03-06</sponsorshipDate>
        <isOriginalCosponsor>True</isOriginalCosponsor>
      </item>
      <item>
        <bioguideId>D000632</bioguideId>
        <fullName>Rep. D'Esposito, Anthony [R-NY-4]</fullName>
        <firstName>Anthony</firstName>
        <lastName>D'Esposito</lastName>
        <party>R</party>
        <state>NY</state>
        <district>4</district>
        <sponsorshipDate>2024-03-06</sponsorshipDate>
        <isOriginalCosponsor>True</isOriginalCosponsor>
      </item>
      <item>
        <bioguideId>G000591</bioguideId>
        <fullName>Rep. Guest, Michael [R-MS-3]</fullName>
        <firstName>Michael</firstName>
        <lastName>Guest</lastName>
        <party>R</party>
        <state>MS</state>
        <district>3</district>
        <sponsorshipDate>2024-03-06</sponsorshipDate>
        <isOriginalCosponsor>True</isOriginalCosponsor>
      </item>
      <item>
        <bioguideId>C001039</bioguideId>
        <fullName>Rep. Cammack, Kat [R-FL-3]</fullName>
        <firstName>Kat</firstName>
        <lastName>Cammack</lastName>
        <party>R</party>
        <state>FL</state>
        <district>3</district>
        <sponsorshipDate>2024-03-06</sponsorshipDate>
        <isOriginalCosponsor>True</isOriginalCosponsor>
      </item>
      <item>
        <bioguideId>D000628</bioguideId>
        <fullName>Rep. Dunn, Neal P. [R-FL-2]</fullName>
        <firstName>Neal</firstName>
        <lastName>Dunn</lastName>
        <party>R</party>
        <state>FL</state>
        <middleName>P.</middleName>
        <district>2</district>
        <sponsorshipDate>2024-03-06</sponsorshipDate>
        <isOriginalCosponsor>True</isOriginalCosponsor>
      </item>
      <item>
        <bioguideId>P000599</bioguideId>
        <fullName>Rep. Posey, Bill [R-FL-8]</fullName>
        <firstName>Bill</firstName>
        <lastName>Posey</lastName>
        <party>R</party>
        <state>FL</state>
        <district>8</district>
        <sponsorshipDate>2024-03-06</sponsorshipDate>
        <isOriginalCosponsor>True</isOriginalCosponsor>
      </item>
      <item>
        <bioguideId>L000599</bioguideId>
        <fullName>Rep. Lawler, Michael [R-NY-17]</fullName>
        <firstName>Michael</firstName>
        <lastName>Lawler</lastName>
        <party>R</party>
        <state>NY</state>
        <district>17</district>
        <sponsorshipDate>2024-03-06</sponsorshipDate>
        <isOriginalCosponsor>True</isOriginalCosponsor>
      </item>
      <item>
        <bioguideId>G000597</bioguideId>
        <fullName>Rep. Garbarino, Andrew R. [R-NY-2]</fullName>
        <firstName>Andrew</firstName>
        <lastName>Garbarino</lastName>
        <party>R</party>
        <state>NY</state>
        <middleName>R.</middleName>
        <district>2</district>
        <sponsorshipDate>2024-03-06</sponsorshipDate>
        <isOriginalCosponsor>True</isOriginalCosponsor>
      </item>
      <item>
        <bioguideId>E000235</bioguideId>
        <fullName>Rep. Ezell, Mike [R-MS-4]</fullName>
        <firstName>Mike</firstName>
        <lastName>Ezell</lastName>
        <party>R</party>
        <state>MS</state>
        <district>4</district>
        <sponsorshipDate>2024-03-06</sponsorshipDate>
        <isOriginalCosponsor>True</isOriginalCosponsor>
      </item>
      <item>
        <bioguideId>G000593</bioguideId>
        <fullName>Rep. Gimenez, Carlos A. [R-FL-28]</fullName>
        <firstName>Carlos</firstName>
        <lastName>Gimenez</lastName>
        <party>R</party>
        <state>FL</state>
        <middleName>A.</middleName>
        <district>28</district>
        <sponsorshipDate>2024-03-06</sponsorshipDate>
        <isOriginalCosponsor>True</isOriginalCosponsor>
      </item>
      <item>
        <bioguideId>H001077</bioguideId>
        <fullName>Rep. Higgins, Clay [R-LA-3]</fullName>
        <firstName>Clay</firstName>
        <lastName>Higgins</lastName>
        <party>R</party>
        <state>LA</state>
        <district>3</district>
        <sponsorshipDate>2024-03-06</sponsorshipDate>
        <isOriginalCosponsor>True</isOriginalCosponsor>
      </item>
      <item>
        <bioguideId>W000806</bioguideId>
        <fullName>Rep. Webster, Daniel [R-FL-11]</fullName>
        <firstName>Daniel</firstName>
        <lastName>Webster</lastName>
        <party>R</party>
        <state>FL</state>
        <district>11</district>
        <sponsorshipDate>2024-03-06</sponsorshipDate>
        <isOriginalCosponsor>True</isOriginalCosponsor>
      </item>
      <item>
        <bioguideId>W000828</bioguideId>
        <fullName>Rep. Williams, Brandon [R-NY-22]</fullName>
        <firstName>Brandon</firstName>
        <lastName>Williams</lastName>
        <party>R</party>
        <state>NY</state>
        <district>22</district>
        <sponsorshipDate>2024-03-06</sponsorshipDate>
        <isOriginalCosponsor>True</isOriginalCosponsor>
      </item>
      <item>
        <bioguideId>K000399</bioguideId>
        <fullName>Rep. Kiggans, Jennifer A. [R-VA-2]</fullName>
        <firstName>Jennifer</firstName>
        <lastName>Kiggans</lastName>
        <party>R</party>
        <state>VA</state>
        <middleName>A.</middleName>
        <district>2</district>
        <sponsorshipDate>2024-03-20</sponsorshipDate>
        <isOriginalCosponsor>False</isOriginalCosponsor>
      </item>
      <item>
        <bioguideId>S001213</bioguideId>
        <fullName>Rep. Steil, Bryan [R-WI-1]</fullName>
        <firstName>Bryan</firstName>
        <lastName>Steil</lastName>
        <party>R</party>
        <state>WI</state>
        <district>1</district>
        <sponsorshipDate>2024-09-20</sponsorshipDate>
        <isOriginalCosponsor>False</isOriginalCosponsor>
      </item>
    </cosponsors>
    <policyArea>
      <name>Immigration</name>
    </policyArea>
    <subjects>
      <legislativeSubjects/>
      <policyArea>
        <name>Immigration</name>
        <updateDate>2024-06-20T14:40:29Z</updateDate>
      </policyArea>
    </subjects>
    <title>CARTEL Act of 2024</title>
    <titles>
      <item>
        <titleType>Display Title</titleType>
        <titleTypeCode>45</titleTypeCode>
        <title>CARTEL Act of 2024</title>
        <updateDate>2024-07-24T15:18:57Z</updateDate>
      </item>
      <item>
        <titleType>Short Title(s) as Introduced</titleType>
        <titleTypeCode>101</titleTypeCode>
        <title>CARTEL Act of 2024</title>
        <updateDate>2024-05-24T13:33:40Z</updateDate>
        <billTextVersionName>Introduced in House</billTextVersionName>
        <billTextVersionCode>IH</billTextVersionCode>
      </item>
      <item>
        <titleType>Short Title(s) as Introduced</titleType>
        <titleTypeCode>101</titleTypeCode>
        <title>Cartel And Radical Terrorist Enforcement Log Act of 2024</title>
        <updateDate>2024-05-24T13:33:40Z</updateDate>
        <billTextVersionName>Introduced in House</billTextVersionName>
        <billTextVersionCode>IH</billTextVersionCode>
      </item>
      <item>
        <titleType>Official Title as Introduced</titleType>
        <titleTypeCode>6</titleTypeCode>
        <title>To publicize U.S. Customs and Border Protection operational statistics and report on foreign terrorist organizations.</title>
        <updateDate>2024-03-28T02:29:10Z</updateDate>
        <billTextVersionName>Introduced in House</billTextVersionName>
        <billTextVersionCode>IH</billTextVersionCode>
      </item>
    </titles>
    <textVersions>
      <item>
        <type>Introduced in House</type>
        <date>2024-03-06T05:00:00Z</date>
        <formats>
          <item>
            <url>https://www.govinfo.gov/content/pkg/BILLS-118hr7566ih/xml/BILLS-118hr7566ih.xml</url>
          </item>
        </formats>
      </item>
    </textVersions>
    <latestAction>
      <actionDate>2024-03-06</actionDate>
      <text>Referred to the Subcommittee on Border Security and Enforcement.</text>
    </latestAction>
  </bill>
  <dublinCore xmlns:dc="http://purl.org/dc/elements/1.1/">
    <dc:format>text/xml</dc:format>
    <dc:language>EN</dc:language>
    <dc:rights>Pursuant to Title 17 Section 105 of the United States Code, this file is not subject to copyright protection and is in the public domain.</dc:rights>
    <dc:contributor>Congressional Research Service, Library of Congress</dc:contributor>
    <dc:description>This file contains bill summaries and statuses for federal legislation. A bill summary describes the most significant provisions of a piece of legislation and details the effects the legislative text may have on current law and federal programs. Bill summaries are authored by the Congressional Research Service (CRS) of the Library of Congress. As stated in Public Law 91-510 (2 USC 166 (d)(6)), one of the duties of CRS is "to prepare summaries and digests of bills and resolutions of a public general nature introduced in the Senate or House of Representatives". For more information, refer to the User Guide that accompanies this file.</dc:description>
  </dublinCore>
</billStatus>
