<?xml version="1.0"?>
<?xml-stylesheet type="text/xsl" href="billres.xsl"?>
<!DOCTYPE bill PUBLIC "-//US Congress//DTDs/bill.dtd//EN" "bill.dtd">
<bill bill-stage="Introduced-in-House" dms-id="H57B48AB3A71A4C90A1E64D6B076312C1" public-private="public" key="H" bill-type="olc"><metadata xmlns:dc="http://purl.org/dc/elements/1.1/">
<dublinCore>
<dc:title>118 HR 2848 IH: Freedom to Move Act</dc:title>
<dc:publisher>U.S. House of Representatives</dc:publisher>
<dc:date>2023-04-25</dc:date>
<dc:format>text/xml</dc:format>
<dc:language>EN</dc:language>
<dc:rights>Pursuant to Title 17 Section 105 of the United States Code, this file is not subject to copyright protection and is in the public domain.</dc:rights>
</dublinCore>
</metadata>
<form>
<distribution-code display="yes">I</distribution-code><congress display="yes">118th CONGRESS</congress><session display="yes">1st Session</session><legis-num display="yes">H. R. 2848</legis-num><current-chamber>IN THE HOUSE OF REPRESENTATIVES</current-chamber><action display="yes"><action-date date="20230425">April 25, 2023</action-date><action-desc><sponsor name-id="P000617">Ms. Pressley</sponsor> introduced the following bill; which was referred to the <committee-name committee-id="HPW00">Committee on Transportation and Infrastructure</committee-name></action-desc></action><legis-type>A BILL</legis-type><official-title display="yes">To direct the Secretary of Transportation to carry out a grant program to support efforts to provide fare-free transit service, and for other purposes.</official-title></form><legis-body id="H5C8709A3E4534032B540122086D318EB" style="OLC"> 
<section id="H95257F01D3CE41BC8D16C682FDBF773F" section-type="section-one"><enum>1.</enum><header>Short title</header><text display-inline="no-display-inline">This Act may be cited as the <quote><short-title>Freedom to Move Act</short-title></quote>.</text></section> <section id="H17CE392042AB4657AD7D4DACE21EBFDE"><enum>2.</enum><header>Purpose</header><text display-inline="no-display-inline">The purposes of this Act are—</text> 
<paragraph id="H028D6AE9CEE147468B4EF506B77EDE98"><enum>(1)</enum><text>to invest in State, county, and local municipalities efforts to provide fare-free public transportation; and</text></paragraph> <paragraph id="H33C2E99268494C80A0391BBEA3639B94"><enum>(2)</enum><text>to support State, county, and local municipalities in improving and expanding access to safe, accessible, and reliable mass transit systems in order to improve the livability of communities.</text></paragraph></section> 
<section id="HA281BF8AF8EC4AEE98D2953D5D45204F"><enum>3.</enum><header>Grants to support fare-free transit</header> 
<subsection id="H9FA24DB4F781410BA7B8F4EC182B9304"><enum>(a)</enum><header>In general</header><text>Not later than 360 days after the date of enactment of this Act, the Secretary shall award grants (which shall be known as <quote>Freedom to Move Grants</quote>) to eligible entities, on a competitive basis, to cover the lost fare revenue for fare-free public transportation and improve public transportation.</text></subsection> <subsection id="H569A2152447E484297BB4A92A7D3D74E"><enum>(b)</enum><header>Application</header><text>To be eligible to receive a grant under this section, an eligible entity shall submit to the Secretary an application at such time, in such manner, and containing such information as the Secretary may require, including, at a minimum, the following:</text> 
<paragraph id="HBE0973AEB5D84822A23BCD214487C3A0"><enum>(1)</enum><text>A description of how the eligible entity plans to implement fare free transit access.</text></paragraph> <paragraph id="H1BFA8591581C47D89F5592039637AB63"><enum>(2)</enum><text>A description of how the entity will work to expand and improve bus service, which may include—</text> 
<subparagraph id="H5E1C6366AE124348936E14193A79BA4C"><enum>(A)</enum><text>a bus network redesign; </text></subparagraph> <subparagraph id="HD02472A3166645DD99BD961BB4FC5191"><enum>(B)</enum><text>how such redesign will prioritize consistent and reliable service for low-income and historically underserved communities;</text></subparagraph> 
<subparagraph id="H92A9BB2A7EB04179A1DC3872C4A00714"><enum>(C)</enum><text>how such redesign will prioritize connectivity to critical services and improve community livability; and</text></subparagraph> <subparagraph id="H5D20B3D6C07F427185B74E8FD4A98E19"><enum>(D)</enum><text>how the eligible entity will meaningfully consult with community, community leaders, local stakeholders and advocates, including transit advocates and disability advocates, local education agencies and institutions of higher education, community developers, labor unions, public housing agencies and workforce development boards, while facilitating such redesign.</text></subparagraph></paragraph> 
<paragraph id="H6030FE186DAA4D1593431114947A2E9B"><enum>(3)</enum><text>A description of how the eligible entity will meaningfully partner and collaborate with community, community leaders, local stakeholders and advocates, including transit advocates and disability advocates, local education agencies and institutions of higher education, community developers, labor unions, public housing agencies and workforce development boards to support outreach efforts to increase awareness of fare-free bus and transit programs.</text></paragraph> <paragraph id="H7A2908430373412FA81C9A54FBE853C6"><enum>(4)</enum><text>A description of the eligible entity’s equity evaluation examining any transit and mobility gaps within the current transit system and how the eligible entity plans to significantly improve these gaps, including—</text> 
<subparagraph id="HE404622CC05E4E9ABB03E8AABF09B902"><enum>(A)</enum><text>the average commute times for driver commuters and non-driver commuters;</text></subparagraph> <subparagraph id="H6C10A2B2AFAF4FF1957450B5FE771615"><enum>(B)</enum><text>public transit ridership rates disaggregated by mode of transportation and demographic group (youth (including youth involved in the foster care system), seniors, individuals with disabilities, and low-income status); and</text></subparagraph> 
<subparagraph id="HC37E8C83C26D4C4CB4091874D00AD3BB"><enum>(C)</enum><text>average length of bus routes and average delay times. </text></subparagraph></paragraph> <paragraph id="H26230F5FDEA648299B4FBC56BB184515"><enum>(5)</enum><text>A description of the eligible entity’s current fare evasion enforcement policies, including—</text> 
<subparagraph id="H4525C6520FA1410FB4EBF720EED56698"><enum>(A)</enum><text>the cost of the fine and whether the infraction is considered a civil offense or a criminal offense punishable by imprisonment;</text></subparagraph> <subparagraph id="H482F09BAA0C641958439073339088E78"><enum>(B)</enum><text>the number of individuals charged with violating a fare evasion policy, disaggregated by age, race, gender, and disability status; and</text></subparagraph> 
<subparagraph id="HF8D8F9CA343F41838F7A9407B0AFB9B7"><enum>(C)</enum><text>how the eligible entity plans to eliminate fare evasion policies and end the criminalization of individuals evading fares.</text></subparagraph></paragraph> <paragraph id="H19160C7D6F0F45D28DCD0F332ECF567C"><enum>(6)</enum><text display-inline="yes-display-inline">An estimate of additional costs as a result of increased ridership, including—</text> 
<subparagraph id="HC753C5B165A848BF9B6C11E41F5B03C0"><enum>(A)</enum><text>fuel;</text></subparagraph> <subparagraph id="HE352A2E9D5D14358B4F3FFD3874E32A6"><enum>(B)</enum><text>personnel;</text></subparagraph> 
<subparagraph id="HDC2328D077E54E8B975330D05993064C"><enum>(C)</enum><text>maintenance; and</text></subparagraph> <subparagraph id="H636C7FBDE7D2456C81CEEAD8FAAEA85A"><enum>(D)</enum><text>other operational costs.</text></subparagraph></paragraph> 
<paragraph id="H785E14D1D38544669E1CEEA338B77CFC"><enum>(7)</enum><text>Information and statistics on assaults on transit employees and a description of trainings and policies to protect employees, which may include de-escalation training.</text></paragraph></subsection> <subsection id="H65B946D16E4742848EA4BD7CBE1AE18D"><enum>(c)</enum><header>Duration</header><text>Grants awarded under this section shall be for a 5-year period.</text></subsection> 
<subsection id="H6A808AACA12D47A89F9249CF04D13E71"><enum>(d)</enum><header>Selection of eligible entities</header><text>In carrying out the program under this section, the Secretary shall award grants to eligible entities located in both rural and urbanized areas. </text></subsection> <subsection id="H8300E22A16114471A8E53FBDA17FF487"><enum>(e)</enum><header>Uses of funds</header><text>An eligible entity that receives a grant under this section shall use such grant to support—</text> 
<paragraph id="H7A85BAEFF4CB4F52B499A0EB7060C552"><enum>(1)</enum><text>implementing a fare-free transit program; and</text></paragraph> <paragraph id="H3B0EAB1E19134F1C89D3A644724CE39A"><enum>(2)</enum><text>efforts to improve public transportation, particularly in underserved communities, including costs associated with efforts to provide more safe, frequent, and reliable bus service, including—</text> 
<subparagraph id="H23E6412A9A6C4E7E9B8CBB706B65B5DD"><enum>(A)</enum><text>bus stop safety and accessibility improvements;</text></subparagraph> <subparagraph id="H43E12FA957C846F8A6F196F8F191BCBF"><enum>(B)</enum><text>pedestrian and bike shelters;</text></subparagraph> 
<subparagraph id="HB6185FFAAD504CBDB6E291B033BFC0D2"><enum>(C)</enum><text>signage;</text></subparagraph> <subparagraph id="H3D66D953F99E4ED3AFEE6215D621C850"><enum>(D)</enum><text>painted bus lanes;</text></subparagraph> 
<subparagraph id="H71A15AE8F5D348BAB18ADB4988860128"><enum>(E)</enum><text>signal priority systems; </text></subparagraph> <subparagraph id="H8E9B05D22FAC422F8C3C7334AEFFCE78"><enum>(F)</enum><text>street redesign; </text></subparagraph> 
<subparagraph id="HCE8A644BD56543DAB82700289A75838E"><enum>(G)</enum><text>operational costs to meet demands of increased ridership, including hiring and training of personnel; and</text></subparagraph> <subparagraph id="HC53884C3EF0443FB80131E7A803C2BFE"><enum>(H)</enum><text>conducting a bus network redesign. </text></subparagraph></paragraph></subsection> 
<subsection id="HE263A4A894CD477A995034178FF04180"><enum>(f)</enum><header>Definitions</header><text>In this section:</text> <paragraph id="H42BB6F90BAFD471D829A188D2079951C"><enum>(1)</enum><header>Eligible entities</header><text>In this section, the term <term>eligible entity</term> means—</text> 
<subparagraph id="HA9D6960B5C894D10AA3F555DB55D90BA"><enum>(A)</enum><text>a State, county, local municipality;</text></subparagraph> <subparagraph id="HBF1EC698537F4C2ABC5C59D1CA9DC76D"><enum>(B)</enum><text>a transit agency;</text></subparagraph> 
<subparagraph id="H5A02372A7B8A4042953E77C39874AEEF"><enum>(C)</enum><text>a private nonprofit organization engaged in public transportation in rural areas; or</text></subparagraph> <subparagraph id="HA5984110E29347228FEECB4A216C2352"><enum>(D)</enum><text>a partnership between entities described in subparagraphs (A) through (C).</text></subparagraph></paragraph> 
<paragraph id="H69349EF5BA974F0AB207E6B9B716F24D"><enum>(2)</enum><header>Underserved community</header><text>The term <term>underserved community</term> means—</text> <subparagraph id="H8754EAD084734F90A9DDE6C49F103030"><enum>(A)</enum><text>a community not served by existing bus routes or infrequent service; and </text></subparagraph> 
<subparagraph id="H60170E0CE1C14BC38F8CD52AEF10F58D"><enum>(B)</enum><text>a community located in an area within a census tract that is identified as—</text> <clause id="HDA210CA45C0349F194371A9D830C0C7E"><enum>(i)</enum><text>a low-income community; and</text></clause> 
<clause id="H4FCFD1D7211246F2A97C1744DA6991D1"><enum>(ii)</enum><text>a community of color.</text></clause></subparagraph></paragraph> <paragraph id="H0F38A09F67534522B82D65E912D93B1B"><enum>(3)</enum><header>Low-income individuals</header><text>The term <term>low-income individuals</term> means an individual whose family income is at or below 150 percent of the poverty line (as that term is defined in section 673(2) of the Community Service Block Grant Act (<external-xref legal-doc="usc" parsable-cite="usc/42/9902">42 U.S.C. 9902(2)</external-xref>), including any revision required by that section) for a family of the size involved.</text></paragraph> 
<paragraph id="H18F3EC6CFFB64AF7A1D6F82FF21F254E"><enum>(4)</enum><header>Foster care youth</header><text>The term <term>foster care youth</term>—</text> <subparagraph id="H07F2DC1912B642CBA0D2762F231F8F08"><enum>(A)</enum><text>means children and youth whose care and placement are the responsibility of the State or Tribal agency that administers a State or Tribal plan under part B or E of title IV of the Social Security Act (<external-xref legal-doc="usc" parsable-cite="usc/42/621">42 U.S.C. 621 et seq.</external-xref> and 670 et seq.), without regard to whether foster care maintenance payments are made under section 472 of such Act (<external-xref legal-doc="usc" parsable-cite="usc/42/672">42 U.S.C. 672</external-xref>) on behalf of such children and youth; and</text></subparagraph> 
<subparagraph id="H60D97579025E4A868E02FD0845B638DB"><enum>(B)</enum><text>includes individuals who were age 13 or older when their care and placement were the responsibility of a State or Tribal agency that administered a State or Tribal plan under part B or E of title IV of the Social Security Act (<external-xref legal-doc="usc" parsable-cite="usc/42/621">42 U.S.C. 621 et seq.</external-xref> and 670 et seq.) and who are no longer under the care and responsibility of such a State or Tribal agency, without regard to any such individual’s subsequent adoption, guardianship arrangement, or other form of permanency outcome.</text></subparagraph></paragraph> <paragraph id="HD167F8858A774A1188E09F9129247BCB"><enum>(5)</enum><header>Public transportation</header><text>The term <term>public transportation</term>—</text> 
<subparagraph id="HF83B86D3C8714C9EA7D3644A0A09DA28"><enum>(A)</enum><text display-inline="yes-display-inline">means regular, continuing shared-ride surface transportation services that are open to the general public or open to a segment of the general public defined by age, disability, or low income; and</text></subparagraph> <subparagraph id="H574E4ECC71AE43F6A2BDDEE483BEC2E1"><enum>(B)</enum><text>does not include—</text> 
<clause id="H35D4579B800E4F9CB5768433F030E262"><enum>(i)</enum><text display-inline="yes-display-inline">intercity passenger rail transportation provided by the entity described in <external-xref legal-doc="usc-chapter" parsable-cite="usc-chapter/49/243">chapter 243</external-xref> of title 49, United States Code, (or a successor to such entity);</text></clause> <clause id="H59FAAF61AB844ABB95AA740AE6675C29"><enum>(ii)</enum><text>intercity bus service;</text></clause> 
<clause id="HFE3558E05A8541EB85C27D5D20CC6FDA"><enum>(iii)</enum><text>charter bus service;</text></clause> <clause id="H5E00C849349547DA9405D044D21F81CD"><enum>(iv)</enum><text>school bus service; </text></clause> 
<clause id="H4CA6370D911F45BFB52BA7D5E3A33EC5"><enum>(v)</enum><text>sightseeing service;</text></clause> <clause id="H70C7E437E30A498BA87AD9200A000E4B"><enum>(vi)</enum><text>courtesy shuttle service for patrons of one or more specific establishments; or</text></clause> 
<clause id="H5053507E786A44A1B3A0C8D06F3492C9"><enum>(vii)</enum><text>intra-terminal or intra-facility shuttle services. </text></clause></subparagraph></paragraph></subsection> <subsection id="HC3F9302B34724645AFF5921E76EDECBD"><enum>(g)</enum><header>Report</header> <paragraph id="H65CD1A87F11E45AAB240AF5407DF7754"><enum>(1)</enum><header>In general</header><text>Not later than 3 years after the date on which funds are made available to carry out this section, the Secretary shall collect data from eligible entities receiving a grant under this section on the progress of meeting the targets described in the application of such entity.</text></paragraph> 
<paragraph id="HEBEEC83EFB1047F1A837A9BA4EA28198"><enum>(2)</enum><header>Requirements</header><text>The report required under paragraph (1) shall—</text> <subparagraph id="H57E97C3C42E04CAA939777670FA9606D"><enum>(A)</enum><text>collect data on demographics of communities served under this Act, disaggregated and cross-tabulated by—</text> 
<clause id="HF3E1D2E3474E43549300F6BE7D288D2D"><enum>(i)</enum><text>race;</text></clause> <clause id="HA655D38653324098BABEEE26DAE85E11"><enum>(ii)</enum><text>ethnicity;</text></clause> 
<clause id="H1E3D2039B9AF40DEB248C4EEED78BA8C"><enum>(iii)</enum><text>sex; and</text></clause> <clause id="H4012139BCF674C1D9F81BD05EE1E63DD"><enum>(iv)</enum><text>household median income; and</text></clause></subparagraph> 
<subparagraph id="H4B70BFCAA19346B3AC1D0F12838DB640"><enum>(B)</enum><text>progress towards significantly closing transit equity gaps as described in subsection (b)(4).</text></subparagraph></paragraph></subsection> <subsection id="H131610F4FC754E1793E7E3CC8343A8F3"><enum>(h)</enum><header>Authorization of appropriations</header><text>There is authorized to be appropriated to carry out this section $5,000,000,000 for each of fiscal years 2024 through 2028.</text></subsection></section> 
</legis-body></bill>

