{"usCongressBioId":"F000441","familyName":"Fletcher","givenName":"Ernest","middleName":"L.","unaccentedFamilyName":"Fletcher","unaccentedGivenName":"Ernest","unaccentedMiddleName":"L.","birthDate":"1952-11-12","birthCirca":false,"birthDateUnknown":false,"deathCirca":false,"image":[{"contentUrl":"/bioguide-staging/assets/dac1e81a1b2f056190d4f1e5ded74259.jpg","caption":"Collection of the U.S. House of Representatives","name":"F000441_001"}],"profileText":"a Representative from Kentucky; born in Mt. Sterling, Montgomery County, Ky., November 12, 1952; graduated from LaFayette High School, Lexington, Ky., 1970; B.S., University of Kentucky College of Engineering, Lexington, Ky., 1974; M.D., University of Kentucky College of Medicine, Lexington, Ky., 1984; United States Air Force, 1974-1979; member of the Kentucky state house of representatives, 1994-1996; elected as a Republican to the One Hundred Sixth Congress and to the two succeeding Congresses and served until his resignation on December 8, 2003 (January 3, 1999-December 8, 2003); Governor of Kentucky, 2003-2007.","relationship":[],"asset":[{"name":"F000441_001","assetType":"Image","contentUrl":"/bioguide-published/assets/dac1e81a1b2f056190d4f1e5ded74259.jpg","creditLine":"Collection of the U.S. House of Representatives","associatedEntity":[],"accessionNumber":"PA2015.02.0019a","usageRight":["Import to Congress.gov"],"uploadDate":"2024-06-21T14:43:50.888","uploadDateISO":"2024-06-21T18:43:50.888Z"}],"jobPositions":[{"job":{"name":"Representative","jobType":"CongressMemberJob"},"congressAffiliation":{"congress":{"name":"The 106th United States Congress","congressNumber":106,"congressType":"USCongress","startDate":"1999-01-03","endDate":"2001-01-03"},"partyAffiliation":[{"party":{"name":"Republican"}}],"caucusAffiliation":[{"party":{"name":"Republican"}}],"represents":{"regionType":"StateRegion","regionCode":"KY"}}},{"job":{"name":"Representative","jobType":"CongressMemberJob"},"congressAffiliation":{"congress":{"name":"The 107th United States Congress","congressNumber":107,"congressType":"USCongress","startDate":"2001-01-03","endDate":"2003-01-03"},"partyAffiliation":[{"party":{"name":"Republican"}}],"caucusAffiliation":[{"party":{"name":"Republican"}}],"represents":{"regionType":"StateRegion","regionCode":"KY"}}},{"job":{"name":"Representative","jobType":"CongressMemberJob"},"startCirca":false,"endDate":"2003-12-08","endCirca":false,"congressAffiliation":{"congress":{"name":"The 108th United States Congress","congressNumber":108,"congressType":"USCongress","startDate":"2003-01-03","endDate":"2005-01-03"},"partyAffiliation":[{"party":{"name":"Republican"},"startCirca":false,"endCirca":false}],"caucusAffiliation":[{"party":{"name":"Republican"},"startCirca":false,"endCirca":false}],"represents":{"regionType":"StateRegion","regionCode":"KY"}},"departureReason":"Resigned"}],"creativeWork":[],"researchRecord":[],"deleted":false}
